jsmb/__init__.py
jsmb-1.0.3.dist-info/LICENSE
jsmb-1.0.3.dist-info/METADATA
jsmb-1.0.3.dist-info/WHEEL
jsmb-1.0.3.dist-info/top_level.txt
jsmb-1.0.3.dist-info/RECORD
