Metadata-Version: 2.1
Name: jsmb
Version: 1.0.3
Summary: Paquete de ayuda para usar SAMBA con Python con smb.
Home-page: https://github.com/xjhonn/jsmb
Author: Jonatan dos Santos da Silva
Author-email: xjhonn@gmail.com
License: UNKNOWN
Platform: UNKNOWN
Classifier: Programming Language :: Python :: 3
Classifier: License :: OSI Approved :: MIT License
Classifier: Operating System :: OS Independent
Requires-Python: >=3.6
